llm_in_sandbox/__init__.py
llm_in_sandbox/action.py
llm_in_sandbox/agent.py
llm_in_sandbox/cli.py
llm_in_sandbox/docker_runtime.py
llm_in_sandbox/observation.py
llm_in_sandbox/tools.py
llm_in_sandbox/trajectory.py
llm_in_sandbox/config/__init__.py
llm_in_sandbox/config/general.yaml
llm_in_sandbox/config/runtime.example.yaml
llm_in_sandbox-0.1.0.data/data/share/llm-in-sandbox/docker/Dockerfile
llm_in_sandbox-0.1.0.dist-info/METADATA
llm_in_sandbox-0.1.0.dist-info/WHEEL
llm_in_sandbox-0.1.0.dist-info/entry_points.txt
llm_in_sandbox-0.1.0.dist-info/licenses/LICENSE
llm_in_sandbox-0.1.0.dist-info/RECORD
