Metadata-Version: 2.4
Name: llm-in-sandbox
Version: 0.1.0
Summary: A lightweight framework that connects LLMs to a virtual computer (Docker-based sandbox) to build general-purpose agents
Project-URL: Homepage, https://github.com/llm-in-sandbox/llm-in-sandbox
Project-URL: Repository, https://github.com/llm-in-sandbox/llm-in-sandbox
Project-URL: Issues, https://github.com/llm-in-sandbox/llm-in-sandbox/issues
Author: Daixuan Cheng, Shaohan Huang
License-Expression: Apache-2.0
License-File: LICENSE
Keywords: agent,agentic-ai,code-sandbox,instruction-following,llm,long-context,mathematics,reinforcement-learning,sandbox,science
Classifier: Development Status :: 4 - Beta
Classifier: Intended Audience :: Developers
Classifier: Intended Audience :: Science/Research
Classifier: License :: OSI Approved :: Apache Software License
Classifier: Operating System :: OS Independent
Classifier: Programming Language :: Python :: 3
Classifier: Programming Language :: Python :: 3.10
Classifier: Programming Language :: Python :: 3.11
Classifier: Programming Language :: Python :: 3.12
Classifier: Topic :: Scientific/Engineering :: Artificial Intelligence
Classifier: Topic :: Scientific/Engineering :: Mathematics
Classifier: Topic :: Software Development :: Libraries :: Python Modules
Requires-Python: >=3.10
Requires-Dist: docker>=6.0.0
Requires-Dist: fire>=0.5.0
Requires-Dist: litellm>=1.0.0
Requires-Dist: pydantic>=2.0.0
Requires-Dist: pyyaml>=6.0
Requires-Dist: rich>=13.0.0
Provides-Extra: dev
Requires-Dist: black>=23.0.0; extra == 'dev'
Requires-Dist: pytest>=7.0.0; extra == 'dev'
Requires-Dist: ruff>=0.1.0; extra == 'dev'
